main.py
rob_dl-0.1.3.dist-info/METADATA
rob_dl-0.1.3.dist-info/WHEEL
rob_dl-0.1.3.dist-info/entry_points.txt
rob_dl-0.1.3.dist-info/top_level.txt
rob_dl-0.1.3.dist-info/RECORD
