Metadata-Version: 2.4
Name: rob-dl
Version: 0.1.3
Summary: rob is a tool that combines curl and yt-dlp to easily download YouTube videos and Files
Requires-Python: >=3.14
Requires-Dist: yt-dlp
